drag/__init__.py
drag/server.py
drag-0.1.3.dist-info/LICENSE.md
drag-0.1.3.dist-info/METADATA
drag-0.1.3.dist-info/WHEEL
drag-0.1.3.dist-info/entry_points.txt
drag-0.1.3.dist-info/top_level.txt
drag-0.1.3.dist-info/RECORD
