Metadata-Version: 2.1
Name: drag
Version: 0.1.3
Summary: Webhook listener dragging along the main Docker process
Home-page: https://gitlab.com/MarcelWaldvogel/drag
Author: Marcel Waldvogel
Author-email: marcel.waldvogel@trifence.ch
License: AGPLv3
Platform: UNKNOWN
Classifier: Development Status :: 3 - Alpha
Classifier: Environment :: No Input/Output (Daemon)
Classifier: Intended Audience :: Information Technology
Classifier: Programming Language :: Python
Classifier: License :: OSI Approved :: MIT License
Classifier: Operating System :: POSIX :: Linux
Classifier: Natural Language :: English
Requires-Python: >=3.7
Requires-Dist: deltat (~=1.1)
Requires-Dist: requests
Requires-Dist: setuptools
